{"展览": [{"开始时间": "2024-07-05", "名称": "杭州·「排球少年!!垃圾场决战」官方授权主题店", "地点": "延安路292号（地铁1号线龙翔桥站D出口） 工联CC", "具体时间范围": "2024.07.05 00:00-07.31 23:59", "想去人数": 115, "最低票价": 38, "Link": "https://show.bilibili.com/platform/detail.html?id=88444", "Cover": "//i1.hdslb.com/bfs/openplatform/202407/kqzjU7571719814631425.jpeg"}, {"开始时间": "2024-07-06", "名称": "杭州·萌忧 动漫游戏嘉年华", "地点": "康候圣街99号 顺丰创新中心", "具体时间范围": "2024.07.06 10:30-07.06 17:00", "想去人数": 1044, "最低票价": 55, "Link": "https://show.bilibili.com/platform/detail.html?id=87292", "Cover": "//i0.hdslb.com/bfs/openplatform/202406/s4DzfyI11718083528496.jpeg"}, {"开始时间": "2024-07-13", "名称": "杭州·AD04动漫展", "地点": "阳城路雅澳杭州电商产业园西侧约200米 杭州大会展中心", "具体时间范围": "2024.07.13 10:00-07.14 17:00", "想去人数": 9248, "最低票价": 75, "Link": "https://show.bilibili.com/platform/detail.html?id=85012", "Cover": "//i0.hdslb.com/bfs/openplatform/202405/y1iKqqnh1715326769523.jpeg"}, {"开始时间": "2024-07-13", "名称": "杭州·AD04动漫展-Pile·内场票", "地点": "阳城路雅澳杭州电商产业园西侧约200米 杭州大会展中心", "具体时间范围": "2024.07.13 09:30-07.13 17:00", "想去人数": 194, "最低票价": 198, "Link": "https://show.bilibili.com/platform/detail.html?id=86819", "Cover": "//i0.hdslb.com/bfs/openplatform/202406/AULfssPJ1717482529866.jpeg"}, {"开始时间": "2024-07-13", "名称": "杭州·AD04动漫展·小泽亚李·内场票", "地点": "阳城路雅澳杭州电商产业园西侧约200米 杭州大会展中心", "具体时间范围": "2024.07.13 09:30-07.13 17:00", "想去人数": 65, "最低票价": 198, "Link": "https://show.bilibili.com/platform/detail.html?id=87241", "Cover": "//i0.hdslb.com/bfs/openplatform/202406/PtX41aGD1718245480604.jpeg"}, {"开始时间": "2024-07-13", "名称": "杭州·代号鸢only-广陵大学", "地点": "康候圣街99号 顺丰创新中心", "具体时间范围": "2024.07.13 09:30-07.13 17:30", "想去人数": 1958, "最低票价": "已售罄", "Link": "https://show.bilibili.com/platform/detail.html?id=83289", "Cover": "//i0.hdslb.com/bfs/openplatform/202406/k2CTTf491718604574410.jpeg"}, {"开始时间": "2024-07-13", "名称": "杭州·草莓动漫节", "地点": "松合路2号 钱塘文体中心", "具体时间范围": "2024.07.13 09:00-07.14 17:00", "想去人数": 6387, "最低票价": 70, "Link": "https://show.bilibili.com/platform/detail.html?id=84229", "Cover": "//i1.hdslb.com/bfs/openplatform/202406/czPRn1ve1718875288240.jpeg"}, {"开始时间": "2024-07-13", "名称": "杭州·草莓动漫节内场票·钱文青", "地点": "松合路2号 钱塘文体中心", "具体时间范围": "2024.07.13 09:00-07.13 17:00", "想去人数": 619, "最低票价": 238, "Link": "https://show.bilibili.com/platform/detail.html?id=84851", "Cover": "//i2.hdslb.com/bfs/openplatform/202406/Vx16dKjM1718875179041.jpeg"}, {"开始时间": "2024-07-14", "名称": "杭州·AD04动漫展-郭馨钰 内场票", "地点": "阳城路雅澳杭州电商产业园西侧约200米 杭州大会展中心", "具体时间范围": "2024.07.14 09:30-07.14 17:00", "想去人数": 66, "最低票价": 298, "Link": "https://show.bilibili.com/platform/detail.html?id=88379", "Cover": "//i1.hdslb.com/bfs/openplatform/202407/UhdkxVlP1719818777634.png"}, {"开始时间": "2024-07-20", "名称": "【会员购严选】杭州·首届次元格子动漫展-进入格子空间，探索次元世界！", "地点": "钱江世纪城奔竞大道353号 杭州国际博览中心", "具体时间范围": "2024.07.20 09:30-07.22 17:00", "想去人数": 9744, "最低票价": 75, "Link": "https://show.bilibili.com/platform/detail.html?id=85616", "Cover": "//i1.hdslb.com/bfs/openplatform/202405/5Dne5VqI1715753018080.jpeg"}, {"开始时间": "2024-07-20", "名称": "杭州·TCD国潮动漫游戏嘉年华", "地点": "阳城路雅澳杭州电商产业园西侧约200米 杭州大会展中心", "具体时间范围": "2024.07.20 09:30-07.21 17:00", "想去人数": 11061, "最低票价": 65, "Link": "https://show.bilibili.com/platform/detail.html?id=85699", "Cover": "//i1.hdslb.com/bfs/openplatform/202406/QzaksReK1718190369702.jpeg"}, {"开始时间": "2024-07-20", "名称": "杭州·次元幻想--二次元全女夜场", "地点": "保淑路2号 The Queen皇后", "具体时间范围": "2024.07.20 13:00-07.20 19:00", "想去人数": 1233, "最低票价": 168, "Link": "https://show.bilibili.com/platform/detail.html?id=81808", "Cover": "//i0.hdslb.com/bfs/openplatform/202406/KEJ8V0WB1718178102884.jpeg"}, {"开始时间": "2024-07-20", "名称": "杭州·生如夏花国乙only·日夜场", "地点": "祥符街道花园岗街181号 格乐利雅婚礼艺术中心(天空之城店)", "具体时间范围": "2024.07.20 10:00-07.20 22:30", "想去人数": 1140, "最低票价": 135, "Link": "https://show.bilibili.com/platform/detail.html?id=85496", "Cover": "//i1.hdslb.com/bfs/openplatform/202405/Qut2ZdAi1715411977772.jpeg"}, {"开始时间": "2024-07-20", "名称": "杭州·第五届华盟次元嘉年华&周年庆狂欢", "地点": "创意路1号 中国智谷富春园区", "具体时间范围": "2024.07.20 10:00-07.21 17:00", "想去人数": 4910, "最低票价": 58, "Link": "https://show.bilibili.com/platform/detail.html?id=84762", "Cover": "//i0.hdslb.com/bfs/openplatform/202404/uE6OVg6T1713885553204.jpeg"}, {"开始时间": "2024-07-20", "名称": "杭州·第四届ArknightsOnly·狼与黑荆棘（明日方舟Only）", "地点": "康候圣街99号 顺丰创新中心", "具体时间范围": "2024.07.20 10:00-07.20 17:00", "想去人数": 790, "最低票价": 79, "Link": "https://show.bilibili.com/platform/detail.html?id=86305", "Cover": "//i1.hdslb.com/bfs/openplatform/202405/cpoiCink1716554216810.png"}, {"开始时间": "2024-07-20", "名称": "杭州·重返未来1999Only2024-UTTU闪烁集会「混沌理论」", "地点": "九环路7号 杭州桔子酒店", "具体时间范围": "2024.07.20 10:00-07.20 17:00", "想去人数": 447, "最低票价": 80, "Link": "https://show.bilibili.com/platform/detail.html?id=87568", "Cover": "//i2.hdslb.com/bfs/openplatform/202406/81Jzaf5S1717561648101.jpeg"}, {"开始时间": "2024-07-20", "名称": "杭州·首届次元格子动漫展嘉宾内场——夙七烈", "地点": "钱江世纪城奔竞大道353号 杭州国际博览中心", "具体时间范围": "2024.07.20 09:00-07.20 17:00", "想去人数": 95, "最低票价": 238, "Link": "https://show.bilibili.com/platform/detail.html?id=86519", "Cover": "//i1.hdslb.com/bfs/openplatform/202405/tRrp8oLo1716953763180.jpeg"}, {"开始时间": "2024-07-20", "名称": "杭州·首届次元格子动漫展嘉宾内场——文森", "地点": "钱江世纪城奔竞大道353号 杭州国际博览中心", "具体时间范围": "2024.07.20 09:00-07.20 17:00", "想去人数": 329, "最低票价": 238, "Link": "https://show.bilibili.com/platform/detail.html?id=86518", "Cover": "//i0.hdslb.com/bfs/openplatform/202405/kwjuTLK31716953514797.jpeg"}, {"开始时间": "2024-07-21", "名称": "杭州·首届次元格子动漫展嘉宾内场——顺子", "地点": "钱江世纪城奔竞大道353号 杭州国际博览中心", "具体时间范围": "2024.07.21 09:00-07.21 17:00", "想去人数": 175, "最低票价": 198, "Link": "https://show.bilibili.com/platform/detail.html?id=86515", "Cover": "//i2.hdslb.com/bfs/openplatform/202405/68FcCJjV1716951469556.jpeg"}, {"开始时间": "2024-07-27", "名称": "杭州·ACG CLUB动漫游戏嘉年华", "地点": "中心路1号 白蓝地文创街区", "具体时间范围": "2024.07.27 10:00-07.27 17:00", "想去人数": 1330, "最低票价": 68.88, "Link": "https://show.bilibili.com/platform/detail.html?id=86265", "Cover": "//i1.hdslb.com/bfs/openplatform/202405/XBRfeQwu1716533419093.jpeg"}, {"开始时间": "2024-07-27", "名称": "杭州·咒术回战ONLY2.0杀青宴", "地点": "丰庆路492号建冠龙禾商务中心A幢 杭州华礼宴国际礼宴中心(龙禾商务中心店)", "具体时间范围": "2024.07.27 10:00-07.27 19:00", "想去人数": 237, "最低票价": 88, "Link": "https://show.bilibili.com/platform/detail.html?id=87527", "Cover": "//i1.hdslb.com/bfs/openplatform/202406/PgbS9Ic01718624347589.jpeg"}, {"开始时间": "2024-07-27", "名称": "杭州·文豪野犬only", "地点": "望江东路333号 杭州瑞莱克斯大酒店", "具体时间范围": "2024.07.27 10:00-07.27 17:00", "想去人数": 877, "最低票价": 54, "Link": "https://show.bilibili.com/platform/detail.html?id=86859", "Cover": "//i1.hdslb.com/bfs/openplatform/202406/LQOrzPac1717473481789.png"}, {"开始时间": "2024-07-27", "名称": "杭州·第五人格only", "地点": "望江东路333号 杭州瑞莱克斯大酒店", "具体时间范围": "2024.07.27 10:00-07.27 17:00", "想去人数": 1231, "最低票价": 60, "Link": "https://show.bilibili.com/platform/detail.html?id=86861", "Cover": "//i1.hdslb.com/bfs/openplatform/202406/ZiqYUjIt1717471158198.jpeg"}, {"开始时间": "2024-07-27", "名称": "杭州·萌忧 原崩铁only", "地点": "康候圣街99号 顺丰创新中心", "具体时间范围": "2024.07.27 10:30-07.27 17:00", "想去人数": 853, "最低票价": 50, "Link": "https://show.bilibili.com/platform/detail.html?id=87913", "Cover": "//i2.hdslb.com/bfs/openplatform/202406/21TFRkof1717573235775.jpeg"}, {"开始时间": "2024-07-28", "名称": "杭州·CrossingX意次元·西湖偶像日Vol.01", "地点": "费家塘路和新北街交叉口 蛙厂RMMF", "具体时间范围": "2024.07.28 12:30-07.28 15:30", "想去人数": 3, "最低票价": 29, "Link": "https://show.bilibili.com/platform/detail.html?id=88487", "Cover": "//i0.hdslb.com/bfs/openplatform/202407/IsF5T0xJ1719906401835.jpeg"}, {"开始时间": "2024-07-28", "名称": "杭州·火影忍者only", "地点": "康候圣街99号 顺丰创新中心", "具体时间范围": "2024.07.28 09:00-07.28 18:00", "想去人数": 2019, "最低票价": 75, "Link": "https://show.bilibili.com/platform/detail.html?id=84243", "Cover": "//i1.hdslb.com/bfs/openplatform/202405/isG309e51715657222196.jpeg"}, {"开始时间": "2024-07-28", "名称": "杭州·第三届百合Only·同好交流", "地点": "望江东路333号 杭州瑞莱克斯大酒店", "具体时间范围": "2024.07.28 10:00-07.28 16:00", "想去人数": 422, "最低票价": 46, "Link": "https://show.bilibili.com/platform/detail.html?id=85895", "Cover": "//i2.hdslb.com/bfs/openplatform/202405/fP3O6LYz1715844791584.jpeg"}, {"开始时间": "2024-07-31", "名称": "杭州·乙游Camerata杭州2.0", "地点": "杭海路601号江和美海洋广场1层 嘉宝丽酒店", "具体时间范围": "2024.07.31 10:00-07.31 17:00", "想去人数": 614, "最低票价": 68, "Link": "https://show.bilibili.com/platform/detail.html?id=86777", "Cover": "//i1.hdslb.com/bfs/openplatform/202406/AparhR671719474456997.jpeg"}, {"开始时间": "2024-08-03", "名称": "杭州·AP动漫游戏嘉年华", "地点": "沈半路171号 Tcar汽车文化主题公园", "具体时间范围": "2024.08.03 09:00-08.04 17:00", "想去人数": 2649, "最低票价": 70, "Link": "https://show.bilibili.com/platform/detail.html?id=85527", "Cover": "//i2.hdslb.com/bfs/openplatform/202405/JbVl16OE1715676665714.jpeg"}, {"开始时间": "2024-08-03", "名称": "杭州·AP动漫游戏嘉年华-赵成晨内场", "地点": "沈半路171号 Tcar汽车文化主题公园", "具体时间范围": "2024.08.03 09:00-08.03 17:00", "想去人数": 306, "最低票价": "已售罄", "Link": "https://show.bilibili.com/platform/detail.html?id=86982", "Cover": "//i0.hdslb.com/bfs/openplatform/202406/ezeRMufU1717561616813.jpeg"}, {"开始时间": "2024-08-03", "名称": "杭州·文豪野犬ONLY", "地点": "康候圣街99号 顺丰创新中心", "具体时间范围": "2024.08.03 10:00-08.03 17:00", "想去人数": 183, "最低票价": 79, "Link": "https://show.bilibili.com/platform/detail.html?id=87115", "Cover": "//i2.hdslb.com/bfs/openplatform/202406/MK5CNQJ61717579320994.jpeg"}, {"开始时间": "2024-08-03", "名称": "杭州·梦漫星河动漫展", "地点": "阳城路雅澳杭州电商产业园西侧约200米 杭州大会展中心", "具体时间范围": "2024.08.03 10:00-08.04 17:00", "想去人数": 1735, "最低票价": 68, "Link": "https://show.bilibili.com/platform/detail.html?id=82836", "Cover": "//i0.hdslb.com/bfs/openplatform/202403/VFfQUJdD1711700169290.jpeg"}, {"开始时间": "2024-08-04", "名称": "杭州·AP动漫游戏嘉年华-紫枫儿内场", "地点": "沈半路171号 Tcar汽车文化主题公园", "具体时间范围": "2024.08.04 09:00-08.04 17:00", "想去人数": 92, "最低票价": 98, "Link": "https://show.bilibili.com/platform/detail.html?id=86650", "Cover": "//i2.hdslb.com/bfs/openplatform/202405/RTC4doV91716964516178.jpeg"}, {"开始时间": "2024-08-10", "名称": "杭州·SK-LiLi综合同人展 × KK WORLD MINI快看漫画乐园", "地点": "鸿泰路与明月桥路交汇处东南角方位(杭港地铁1号线/杭州地铁4号线彭埠站D口20米) 港龙悠乐城", "具体时间范围": "2024.08.10 10:00-08.11 17:00", "想去人数": 793, "最低票价": 68, "Link": "https://show.bilibili.com/platform/detail.html?id=88062", "Cover": "//i2.hdslb.com/bfs/openplatform/202406/xlLi5AXx1719324778808.jpeg"}, {"开始时间": "2024-08-10", "名称": "杭州·原神X崩坏X星铁旅行盛宴·首展", "地点": "德胜东路2539号 梦马汽车小镇", "具体时间范围": "2024.08.10 10:00-08.11 17:00", "想去人数": 45, "最低票价": 65, "Link": "https://show.bilibili.com/platform/detail.html?id=88429", "Cover": "//i1.hdslb.com/bfs/openplatform/202407/1oKYAwlD1719816495200.png"}, {"开始时间": "2024-08-10", "名称": "杭州·原神X星铁X绝区零only", "地点": "望江东路333号 杭州瑞莱克斯大酒店", "具体时间范围": "2024.08.10 10:00-08.10 17:00", "想去人数": 912, "最低票价": 60, "Link": "https://show.bilibili.com/platform/detail.html?id=82754", "Cover": "//i1.hdslb.com/bfs/openplatform/202403/qA0LNJuF1710234461030.jpeg"}, {"开始时间": "2024-08-10", "名称": "杭州·造梦探险家城堡二次元同好会", "地点": "大岭山路156号 爱丽芬城堡", "具体时间范围": "2024.08.10 10:00-08.10 22:00", "想去人数": 589, "最低票价": 38, "Link": "https://show.bilibili.com/platform/detail.html?id=86432", "Cover": "//i2.hdslb.com/bfs/openplatform/202405/xWUy30Ns1716783723057.jpeg"}, {"开始时间": "2024-08-10", "名称": "杭州·首届LoveLive Only", "地点": "同协路288号 1928创意园", "具体时间范围": "2024.08.10 10:00-08.10 22:00", "想去人数": 16, "最低票价": 28, "Link": "https://show.bilibili.com/platform/detail.html?id=88458", "Cover": "//i1.hdslb.com/bfs/openplatform/202406/cT9gANGo1719481033302.png"}, {"开始时间": "2024-08-17", "名称": "【会员购严选】杭州·首届次元之门动漫游戏博览会", "地点": "阳城路雅澳杭州电商产业园西侧约200米 杭州大会展中心", "具体时间范围": "2024.08.17 10:00-08.18 17:30", "想去人数": 3304, "最低票价": 75, "Link": "https://show.bilibili.com/platform/detail.html?id=87065", "Cover": "//i1.hdslb.com/bfs/openplatform/202406/wrxORgrP1717593610187.jpeg"}, {"开始时间": "2024-08-17", "名称": "浙江·马娘ONLY03-晴风游憩", "地点": "康候圣街99号 顺丰创新中心", "具体时间范围": "2024.08.17 10:00-08.17 17:00", "想去人数": 234, "最低票价": 68, "Link": "https://show.bilibili.com/platform/detail.html?id=86529", "Cover": "//i1.hdslb.com/bfs/openplatform/202405/21d6moub1716799089058.jpeg"}, {"开始时间": "2024-08-18", "名称": "杭州·少女番only3.0", "地点": "凤起东路211号 名人名家宴会艺术中心(顺福店)", "具体时间范围": "2024.08.18 10:00-08.18 17:00", "想去人数": 81, "最低票价": 89, "Link": "https://show.bilibili.com/platform/detail.html?id=87676", "Cover": "//i1.hdslb.com/bfs/openplatform/202406/VHJXciCn1718433428129.jpeg"}, {"开始时间": "2024-08-18", "名称": "浙江·蔚蓝档案ONLY02-夏末狂欢！", "地点": "康候圣街99号 顺丰创新中心", "具体时间范围": "2024.08.18 10:00-08.18 17:00", "想去人数": 505, "最低票价": 68, "Link": "https://show.bilibili.com/platform/detail.html?id=86594", "Cover": "//i1.hdslb.com/bfs/openplatform/202405/TVvJFURG1716799911888.jpeg"}, {"开始时间": "2024-08-24", "名称": "杭州·D3动漫游戏嘉年华", "地点": "德胜东路2539号 梦马汽车小镇", "具体时间范围": "2024.08.24 10:00-08.24 17:00", "想去人数": 575, "最低票价": 50, "Link": "https://show.bilibili.com/platform/detail.html?id=84912", "Cover": "//i0.hdslb.com/bfs/openplatform/202406/LC5aplda1718697399055.jpeg"}, {"开始时间": "2024-08-24", "名称": "杭州·奶司的小人国娃展Nice Mini World", "地点": "凤起东路211号 名人名家宴会艺术中心(顺福店)", "具体时间范围": "2024.08.24 10:30-08.24 17:00", "想去人数": 27, "最低票价": 60, "Link": "https://show.bilibili.com/platform/detail.html?id=86954", "Cover": "//i0.hdslb.com/bfs/openplatform/202406/aeSvo0X71717659096631.png"}, {"开始时间": "2024-08-24", "名称": "杭州·萌忧·原崩铁only", "地点": "康候圣街99号 顺丰创新中心", "具体时间范围": "2024.08.24 10:30-08.24 17:00", "想去人数": 894, "最低票价": 50, "Link": "https://show.bilibili.com/platform/detail.html?id=87293", "Cover": "//i2.hdslb.com/bfs/openplatform/202406/rQFz5smR1717475284585.jpeg"}, {"开始时间": "2024-08-24", "名称": "杭州·金魂ONLY", "地点": "金一路79号 XPACE湾区数字公园", "具体时间范围": "2024.08.24 10:00-08.24 18:00", "想去人数": 235, "最低票价": 78, "Link": "https://show.bilibili.com/platform/detail.html?id=87230", "Cover": "//i2.hdslb.com/bfs/openplatform/202406/SfNdoHfv1718176444920.png"}, {"开始时间": "2024-09-15", "名称": "杭州·浮游猫动漫嘉年华", "地点": "鸿泰路与明月桥路交汇处东南角方位(杭港地铁1号线/杭州地铁4号线彭埠站D口20米) 港龙悠乐城", "具体时间范围": "2024.09.15 09:00-09.16 18:00", "想去人数": 3, "最低票价": 68, "Link": "https://show.bilibili.com/platform/detail.html?id=88498", "Cover": "//i2.hdslb.com/bfs/openplatform/202406/qsuFy4iv1719569431608.jpeg"}, {"开始时间": "2024-09-15", "名称": "杭州·理想乡动漫展-同人创作者大会", "地点": "阳城路雅澳杭州电商产业园西侧约200米 杭州大会展中心", "具体时间范围": "2024.09.15 10:00-09.16 17:00", "想去人数": 4200, "最低票价": 1, "Link": "https://show.bilibili.com/platform/detail.html?id=83822", "Cover": "//i2.hdslb.com/bfs/openplatform/202404/GGEZUjGw1711959030111.png"}], "演出": [{"开始时间": "2024-07-10", "名称": "杭州·《爱·永恒》理查德·克莱德曼钢琴音乐会", "地点": "杭州市西湖区省府路9号 浙江省人民大会堂", "具体时间范围": "2024.07.10 19:30-07.10 21:00", "想去人数": 18, "最低票价": "不可售", "Link": "https://show.bilibili.com/platform/detail.html?id=83948", "Cover": "//i1.hdslb.com/bfs/openplatform/202404/huCPMql51712639746482.jpeg"}, {"开始时间": "2024-07-13", "名称": "杭州·【早鸟4折】《海上钢琴师1900》一生必听经典电影主题音乐会", "地点": "湖墅南路138号 杭州浙话艺术剧院", "具体时间范围": "2024.07.13 14:00-07.13 15:30", "想去人数": 10, "最低票价": 72, "Link": "https://show.bilibili.com/platform/detail.html?id=87485", "Cover": "//i0.hdslb.com/bfs/openplatform/202406/alBf4PMZ1718607067950.jpeg"}, {"开始时间": "2024-07-13", "名称": "杭州·【早鸟5折】致敬大师·告别之作《你想活出怎样的人生》-宫崎骏&久石让 经典动漫作品音乐会（取消）", "地点": "湖墅南路136-138号 浙话艺术剧院", "具体时间范围": "2024.07.13 14:00-07.13 15:30", "想去人数": 16, "最低票价": "不可售", "Link": "https://show.bilibili.com/platform/detail.html?id=85010", "Cover": "//i2.hdslb.com/bfs/openplatform/202404/tH3Af4Du1714378126407.jpeg"}, {"开始时间": "2024-07-13", "名称": "杭州·【早鸟6折】《忱宴·渐渐被你吸引》热血动漫二次元ACG演唱会", "地点": "湖墅南路136-138号 浙话艺术剧院", "具体时间范围": "2024.07.13 19:30-07.13 21:30", "想去人数": 28, "最低票价": 60, "Link": "https://show.bilibili.com/platform/detail.html?id=85011", "Cover": "//i1.hdslb.com/bfs/openplatform/202404/2Gd8eLva1714379746993.jpeg"}, {"开始时间": "2024-07-13", "名称": "杭州·海上钢琴师—一生必听的电影名曲《泰坦尼克号》《花样年华》《海上钢琴师》", "地点": "曙光路31号 浙江音乐厅", "具体时间范围": "2024.07.13 19:30-07.13 21:00", "想去人数": 10, "最低票价": 100, "Link": "https://show.bilibili.com/platform/detail.html?id=85889", "Cover": "//i0.hdslb.com/bfs/openplatform/202405/52kxbBTh1716096935602.jpeg"}, {"开始时间": "2024-07-19", "名称": "杭州·【限时8折】卓别林影片改编喜剧《寻子遇仙后记》", "地点": "留泗路东山里22号 大美创意园-2号楼", "具体时间范围": "2024.07.19 19:30-07.20 15:30", "想去人数": 0, "最低票价": 80, "Link": "https://show.bilibili.com/platform/detail.html?id=87369", "Cover": "//i1.hdslb.com/bfs/openplatform/202406/HqQMhpXC1718336795641.png"}, {"开始时间": "2024-07-20", "名称": "杭州·《天空之城》久石让宫崎骏经典作品音乐会", "地点": "曙光路31号 浙江音乐厅", "具体时间范围": "2024.07.20 19:30-07.20 21:00", "想去人数": 30, "最低票价": 100, "Link": "https://show.bilibili.com/platform/detail.html?id=85890", "Cover": "//i0.hdslb.com/bfs/openplatform/202405/05o0L8tp1716097893125.jpeg"}, {"开始时间": "2024-07-21", "名称": "杭州·《似锦》沉浸式疗愈烛光音乐会", "地点": "留泗路东山里22号 大美创意园-2号楼", "具体时间范围": "2024.07.21 15:00-07.21 16:00", "想去人数": 1, "最低票价": 88, "Link": "https://show.bilibili.com/platform/detail.html?id=87376", "Cover": "//i0.hdslb.com/bfs/openplatform/202406/FZx6iPGK1718334063807.jpeg"}, {"开始时间": "2024-07-25", "名称": " 杭州·交响摇滚版《风暴》墨西哥时空乐队 &电子古典跨界音乐会", "地点": "中山南路77号尚城·利星1157 3F MAOLivehouse杭州", "具体时间范围": "2024.07.25 20:00-07.25 21:30", "想去人数": 0, "最低票价": 180, "Link": "https://show.bilibili.com/platform/detail.html?id=88086", "Cover": "//i0.hdslb.com/bfs/openplatform/202406/4ItW5lec1719371098332.jpeg"}, {"开始时间": "2024-07-26", "名称": "杭州·系统任务：重生之我是音乐一体机！王子健2024巡回演出", "地点": "金沙大道盈都吾角广场 ECHO SPACE(龙湖杭州吾角天街)", "具体时间范围": "2024.07.26 20:00-07.26 22:00", "想去人数": 65, "最低票价": 128, "Link": "https://show.bilibili.com/platform/detail.html?id=87586", "Cover": "//i0.hdslb.com/bfs/openplatform/202406/CnON9Cof1718675822055.jpeg"}, {"开始时间": "2024-07-27", "名称": "杭州·黄西全新脱口秀专场《水土不服》", "地点": "延安路279号 浙江胜利剧院", "具体时间范围": "2024.07.27 14:30-07.27 21:30", "想去人数": 5, "最低票价": 180, "Link": "https://show.bilibili.com/platform/detail.html?id=85935", "Cover": "//i2.hdslb.com/bfs/openplatform/202405/9YqhR4Ke1716191781870.jpeg"}, {"开始时间": "2024-08-02", "名称": "杭州·【限时8折】约瑟夫·格雷夫斯话剧新作《海森堡》", "地点": "留泗路东山里22号 大美创意园-2号楼", "具体时间范围": "2024.08.02 19:30-08.03 15:30", "想去人数": 0, "最低票价": 80, "Link": "https://show.bilibili.com/platform/detail.html?id=87370", "Cover": "//i1.hdslb.com/bfs/openplatform/202406/sDSn3j1w1718337517231.jpeg"}, {"开始时间": "2024-08-03", "名称": "杭州·《从古典到浪漫》抒情室内音乐会-浙江电影爱乐乐团雅岚弦乐四重奏", "地点": "曙光路31号 浙江音乐厅", "具体时间范围": "2024.08.03 19:30-08.03 21:00", "想去人数": 5, "最低票价": 100, "Link": "https://show.bilibili.com/platform/detail.html?id=85892", "Cover": "//i0.hdslb.com/bfs/openplatform/202405/brZcPOD11716106717403.jpeg"}, {"开始时间": "2024-08-04", "名称": "杭州·井草圣二 2024《夏日独白》指弹吉他音乐会", "地点": "中山南路77号尚城1157利星3楼 MAO Livehouse（杭州）", "具体时间范围": "2024.08.04 19:30-08.04 21:00", "想去人数": 5, "最低票价": 260, "Link": "https://show.bilibili.com/platform/detail.html?id=86939", "Cover": "//i2.hdslb.com/bfs/openplatform/202406/12K7MVMZ1717643805476.jpeg"}, {"开始时间": "2024-08-06", "名称": "杭州·新西兰治愈系民谣歌手Luke Thompson2024中国巡演 KEEP ROLLING ON ", "地点": "万塘汇城市生活广场南楼2F 9-Club LIVEHOUSE", "具体时间范围": "2024.08.06 20:00-08.06 21:30", "想去人数": 0, "最低票价": 180, "Link": "https://show.bilibili.com/platform/detail.html?id=88362", "Cover": "//i0.hdslb.com/bfs/openplatform/202406/uIvGqSyP1719739616478.jpeg"}, {"开始时间": "2024-08-10", "名称": "杭州·“不能说的秘密”七夕专场浪漫烛光音乐会", "地点": "留泗路东山里22号 大美创意园-2号楼", "具体时间范围": "2024.08.10 19:30-08.10 21:00", "想去人数": 5, "最低票价": 100, "Link": "https://show.bilibili.com/platform/detail.html?id=87371", "Cover": "//i0.hdslb.com/bfs/openplatform/202406/zMFLTA9h1718332607508.jpeg"}, {"开始时间": "2024-08-10", "名称": "杭州·《LALALAND爱乐之城》浪漫主题音乐会", "地点": "武林路77号 浙江省文化馆小剧场（原群艺馆小剧场）", "具体时间范围": "2024.08.10 14:30-08.10 16:00", "想去人数": 10, "最低票价": 100, "Link": "https://show.bilibili.com/platform/detail.html?id=86928", "Cover": "//i2.hdslb.com/bfs/openplatform/202406/WRJvvYJV1717575030302.jpeg"}, {"开始时间": "2024-08-10", "名称": "杭州·【七夕巨献·早鸟4折】《爱乐之城》经典浪漫影视名曲音乐会", "地点": "湖墅南路138号 杭州浙话艺术剧院", "具体时间范围": "2024.08.10 14:00-08.10 15:30", "想去人数": 9, "最低票价": 48, "Link": "https://show.bilibili.com/platform/detail.html?id=87682", "Cover": "//i2.hdslb.com/bfs/openplatform/202406/i3KOxYoS1718781845754.jpeg"}, {"开始时间": "2024-08-10", "名称": "杭州·【七夕巨献·早鸟6折】真的爱你”致敬Beyond·黄家驹31周年演唱会·630乐团再现91殿堂级演出", "地点": "湖墅南路136-138号 浙话艺术剧院", "具体时间范围": "2024.08.10 19:30-08.10 21:30", "想去人数": 5, "最低票价": 60, "Link": "https://show.bilibili.com/platform/detail.html?id=85333", "Cover": "//i1.hdslb.com/bfs/openplatform/202405/uYt32zt21715221330023.jpeg"}, {"开始时间": "2024-08-10", "名称": "杭州·七夕特辑·《红楼梦》国风古典主题音乐会", "地点": "武林路77号 浙江省文化馆小剧场（原群艺馆小剧场）", "具体时间范围": "2024.08.10 19:30-08.10 21:00", "想去人数": 9, "最低票价": 100, "Link": "https://show.bilibili.com/platform/detail.html?id=87221", "Cover": "//i1.hdslb.com/bfs/openplatform/202406/AE6vRAZN1718172406972.jpeg"}, {"开始时间": "2024-08-10", "名称": "杭州·吹响号角狩猎吧—怪物猎人&最终幻想&塞尔达 热血游戏视听音乐会", "地点": "杭州市江干区新业路39号 杭州大剧院(音乐厅)", "具体时间范围": "2024.08.10 19:30-08.10 21:00", "想去人数": 67, "最低票价": 180, "Link": "https://show.bilibili.com/platform/detail.html?id=84879", "Cover": "//i0.hdslb.com/bfs/openplatform/202404/jJcWHuGa1714010818763.jpeg"}, {"开始时间": "2024-08-10", "名称": "杭州·追逐动漫的旋律—二次元音符的魔法 经典动漫ACG视听音乐会", "地点": "杭州市江干区新业路39号 杭州大剧院(音乐厅)", "具体时间范围": "2024.08.10 14:30-08.10 16:00", "想去人数": 67, "最低票价": 180, "Link": "https://show.bilibili.com/platform/detail.html?id=84898", "Cover": "//i2.hdslb.com/bfs/openplatform/202404/75j1xIzA1714102078044.jpeg"}, {"开始时间": "2024-08-16", "名称": "杭州·Marcin Patrzalek 2024 《原声之龙》指弹吉他音乐会", "地点": "新北街85号三层 66livehouse", "具体时间范围": "2024.08.16 19:30-08.16 21:00", "想去人数": 104, "最低票价": "已售罄", "Link": "https://show.bilibili.com/platform/detail.html?id=86294", "Cover": "//i2.hdslb.com/bfs/openplatform/202405/sbxCQPzr1716547720261.jpeg"}, {"开始时间": "2024-08-17", "名称": "杭州·动漫作品主题音乐会-《火影忍者》《海贼王》《灌篮高手》", "地点": "曙光路31号 浙江音乐厅", "具体时间范围": "2024.08.17 19:30-08.17 21:00", "想去人数": 42, "最低票价": 100, "Link": "https://show.bilibili.com/platform/detail.html?id=85891", "Cover": "//i1.hdslb.com/bfs/openplatform/202405/ei0H7pZr1716099647338.jpeg"}, {"开始时间": "2024-09-07", "名称": "杭州·《卡农》永恒经典名曲音乐会", "地点": "曙光路31号 浙江音乐厅", "具体时间范围": "2024.09.07 19:30-09.07 21:00", "想去人数": 2, "最低票价": 100, "Link": "https://show.bilibili.com/platform/detail.html?id=85894", "Cover": "//i2.hdslb.com/bfs/openplatform/202405/3jz9YpaW1716100738530.jpeg"}, {"开始时间": "2024-11-01", "名称": "杭州·阿加莎•克里斯蒂经典悬疑剧《无人生还》", "地点": "武林广场29号 杭州剧院", "具体时间范围": "2024.11.01 19:30-11.03 17:00", "想去人数": 59, "最低票价": 380, "Link": "https://show.bilibili.com/platform/detail.html?id=82776", "Cover": "//i0.hdslb.com/bfs/openplatform/202403/K55FY9vh1710298068131.jpeg"}, {"开始时间": "2024-12-24", "名称": "杭州·百老汇悬疑惊悚喜剧《死亡陷阱》", "地点": "武林广场29号 杭州剧院", "具体时间范围": "2024.12.24 19:30-12.25 22:35", "想去人数": 1, "最低票价": 280, "Link": "https://show.bilibili.com/platform/detail.html?id=88084", "Cover": "//i1.hdslb.com/bfs/openplatform/202407/KIysvIdZ1719818362132.jpeg"}], "本地生活": [{"开始时间": "2024-06-08", "名称": "杭州·木灵动漫 某某主题餐厅", "地点": "平海路124号 杭州湖滨88", "具体时间范围": "2024.06.08 00:00-07.21 23:59", "想去人数": 5888, "最低票价": "已售罄", "Link": "https://show.bilibili.com/platform/detail.html?id=86604", "Cover": "//i2.hdslb.com/bfs/openplatform/202405/vynNa5N71717058842316.jpeg"}], "全部类型": [{"开始时间": "2024-07-06", "名称": "杭州·萌忧 动漫游戏嘉年华", "地点": "康候圣街99号 顺丰创新中心", "具体时间范围": "2024.07.06 10:30-07.06 17:00", "想去人数": 1044, "最低票价": 55.0, "Link": "https://show.bilibili.com/platform/detail.html?id=87292", "Cover": "//i0.hdslb.com/bfs/openplatform/202406/s4DzfyI11718083528496.jpeg"}, {"开始时间": "2024-07-13", "名称": "杭州·AD04动漫展", "地点": "阳城路雅澳杭州电商产业园西侧约200米 杭州大会展中心", "具体时间范围": "2024.07.13 10:00-07.14 17:00", "想去人数": 9248, "最低票价": 75.0, "Link": "https://show.bilibili.com/platform/detail.html?id=85012", "Cover": "//i0.hdslb.com/bfs/openplatform/202405/y1iKqqnh1715326769523.jpeg"}, {"开始时间": "2024-07-13", "名称": "杭州·AD04动漫展·小泽亚李·内场票", "地点": "阳城路雅澳杭州电商产业园西侧约200米 杭州大会展中心", "具体时间范围": "2024.07.13 09:30-07.13 17:00", "想去人数": 65, "最低票价": 198.0, "Link": "https://show.bilibili.com/platform/detail.html?id=87241", "Cover": "//i0.hdslb.com/bfs/openplatform/202406/PtX41aGD1718245480604.jpeg"}, {"开始时间": "2024-07-13", "名称": "杭州·【早鸟4折】《海上钢琴师1900》一生必听经典电影主题音乐会", "地点": "湖墅南路138号 杭州浙话艺术剧院", "具体时间范围": "2024.07.13 14:00-07.13 15:30", "想去人数": 10, "最低票价": 72.0, "Link": "https://show.bilibili.com/platform/detail.html?id=87485", "Cover": "//i0.hdslb.com/bfs/openplatform/202406/alBf4PMZ1718607067950.jpeg"}, {"开始时间": "2024-07-13", "名称": "杭州·海上钢琴师—一生必听的电影名曲《泰坦尼克号》《花样年华》《海上钢琴师》", "地点": "曙光路31号 浙江音乐厅", "具体时间范围": "2024.07.13 19:30-07.13 21:00", "想去人数": 10, "最低票价": 100.0, "Link": "https://show.bilibili.com/platform/detail.html?id=85889", "Cover": "//i0.hdslb.com/bfs/openplatform/202405/52kxbBTh1716096935602.jpeg"}, {"开始时间": "2024-07-13", "名称": "杭州·草莓动漫节", "地点": "松合路2号 钱塘文体中心", "具体时间范围": "2024.07.13 09:00-07.14 17:00", "想去人数": 6387, "最低票价": 70.0, "Link": "https://show.bilibili.com/platform/detail.html?id=84229", "Cover": "//i1.hdslb.com/bfs/openplatform/202406/czPRn1ve1718875288240.jpeg"}, {"开始时间": "2024-07-13", "名称": "杭州·草莓动漫节内场票·钱文青", "地点": "松合路2号 钱塘文体中心", "具体时间范围": "2024.07.13 09:00-07.13 17:00", "想去人数": 619, "最低票价": 238.0, "Link": "https://show.bilibili.com/platform/detail.html?id=84851", "Cover": "//i2.hdslb.com/bfs/openplatform/202406/Vx16dKjM1718875179041.jpeg"}, {"开始时间": "2024-07-20", "名称": "【会员购严选】杭州·首届次元格子动漫展-进入格子空间，探索次元世界！", "地点": "钱江世纪城奔竞大道353号 杭州国际博览中心", "具体时间范围": "2024.07.20 09:30-07.22 17:00", "想去人数": 9744, "最低票价": 75.0, "Link": "https://show.bilibili.com/platform/detail.html?id=85616", "Cover": "//i1.hdslb.com/bfs/openplatform/202405/5Dne5VqI1715753018080.jpeg"}, {"开始时间": "2024-07-20", "名称": "杭州·TCD国潮动漫游戏嘉年华", "地点": "阳城路雅澳杭州电商产业园西侧约200米 杭州大会展中心", "具体时间范围": "2024.07.20 09:30-07.21 17:00", "想去人数": 11061, "最低票价": 65.0, "Link": "https://show.bilibili.com/platform/detail.html?id=85699", "Cover": "//i1.hdslb.com/bfs/openplatform/202406/QzaksReK1718190369702.jpeg"}, {"开始时间": "2024-07-20", "名称": "杭州·《天空之城》久石让宫崎骏经典作品音乐会", "地点": "曙光路31号 浙江音乐厅", "具体时间范围": "2024.07.20 19:30-07.20 21:00", "想去人数": 30, "最低票价": 100.0, "Link": "https://show.bilibili.com/platform/detail.html?id=85890", "Cover": "//i0.hdslb.com/bfs/openplatform/202405/05o0L8tp1716097893125.jpeg"}, {"开始时间": "2024-07-20", "名称": "杭州·次元幻想--二次元全女夜场", "地点": "保淑路2号 The Queen皇后", "具体时间范围": "2024.07.20 13:00-07.20 19:00", "想去人数": 1233, "最低票价": 168.0, "Link": "https://show.bilibili.com/platform/detail.html?id=81808", "Cover": "//i0.hdslb.com/bfs/openplatform/202406/KEJ8V0WB1718178102884.jpeg"}, {"开始时间": "2024-07-20", "名称": "杭州·生如夏花国乙only·日夜场", "地点": "祥符街道花园岗街181号 格乐利雅婚礼艺术中心(天空之城店)", "具体时间范围": "2024.07.20 10:00-07.20 22:30", "想去人数": 1140, "最低票价": 135.0, "Link": "https://show.bilibili.com/platform/detail.html?id=85496", "Cover": "//i1.hdslb.com/bfs/openplatform/202405/Qut2ZdAi1715411977772.jpeg"}, {"开始时间": "2024-07-20", "名称": "杭州·第五届华盟次元嘉年华&周年庆狂欢", "地点": "创意路1号 中国智谷富春园区", "具体时间范围": "2024.07.20 10:00-07.21 17:00", "想去人数": 4910, "最低票价": 58.0, "Link": "https://show.bilibili.com/platform/detail.html?id=84762", "Cover": "//i0.hdslb.com/bfs/openplatform/202404/uE6OVg6T1713885553204.jpeg"}, {"开始时间": "2024-07-20", "名称": "杭州·第四届ArknightsOnly·狼与黑荆棘（明日方舟Only）", "地点": "康候圣街99号 顺丰创新中心", "具体时间范围": "2024.07.20 10:00-07.20 17:00", "想去人数": 790, "最低票价": 79.0, "Link": "https://show.bilibili.com/platform/detail.html?id=86305", "Cover": "//i1.hdslb.com/bfs/openplatform/202405/cpoiCink1716554216810.png"}, {"开始时间": "2024-07-20", "名称": "杭州·重返未来1999Only2024-UTTU闪烁集会「混沌理论」", "地点": "九环路7号 杭州桔子酒店", "具体时间范围": "2024.07.20 10:00-07.20 17:00", "想去人数": 447, "最低票价": 80.0, "Link": "https://show.bilibili.com/platform/detail.html?id=87568", "Cover": "//i2.hdslb.com/bfs/openplatform/202406/81Jzaf5S1717561648101.jpeg"}, {"开始时间": "2024-07-21", "名称": "杭州·《似锦》沉浸式疗愈烛光音乐会", "地点": "留泗路东山里22号 大美创意园-2号楼", "具体时间范围": "2024.07.21 15:00-07.21 16:00", "想去人数": 1, "最低票价": 88.0, "Link": "https://show.bilibili.com/platform/detail.html?id=87376", "Cover": "//i0.hdslb.com/bfs/openplatform/202406/FZx6iPGK1718334063807.jpeg"}, {"开始时间": "2024-07-21", "名称": "杭州·首届次元格子动漫展嘉宾内场——顺子", "地点": "钱江世纪城奔竞大道353号 杭州国际博览中心", "具体时间范围": "2024.07.21 09:00-07.21 17:00", "想去人数": 175, "最低票价": 198.0, "Link": "https://show.bilibili.com/platform/detail.html?id=86515", "Cover": "//i2.hdslb.com/bfs/openplatform/202405/68FcCJjV1716951469556.jpeg"}, {"开始时间": "2024-07-26", "名称": "杭州·系统任务：重生之我是音乐一体机！王子健2024巡回演出", "地点": "金沙大道盈都吾角广场 ECHO SPACE(龙湖杭州吾角天街)", "具体时间范围": "2024.07.26 20:00-07.26 22:00", "想去人数": 65, "最低票价": 128.0, "Link": "https://show.bilibili.com/platform/detail.html?id=87586", "Cover": "//i0.hdslb.com/bfs/openplatform/202406/CnON9Cof1718675822055.jpeg"}, {"开始时间": "2024-07-27", "名称": "杭州·ACG CLUB动漫游戏嘉年华", "地点": "中心路1号 白蓝地文创街区", "具体时间范围": "2024.07.27 10:00-07.27 17:00", "想去人数": 1330, "最低票价": 68.88, "Link": "https://show.bilibili.com/platform/detail.html?id=86265", "Cover": "//i1.hdslb.com/bfs/openplatform/202405/XBRfeQwu1716533419093.jpeg"}, {"开始时间": "2024-07-27", "名称": "杭州·咒术回战ONLY2.0杀青宴", "地点": "丰庆路492号建冠龙禾商务中心A幢 杭州华礼宴国际礼宴中心(龙禾商务中心店)", "具体时间范围": "2024.07.27 10:00-07.27 19:00", "想去人数": 237, "最低票价": 88.0, "Link": "https://show.bilibili.com/platform/detail.html?id=87527", "Cover": "//i1.hdslb.com/bfs/openplatform/202406/PgbS9Ic01718624347589.jpeg"}, {"开始时间": "2024-07-27", "名称": "杭州·文豪野犬only", "地点": "望江东路333号 杭州瑞莱克斯大酒店", "具体时间范围": "2024.07.27 10:00-07.27 17:00", "想去人数": 877, "最低票价": 54.0, "Link": "https://show.bilibili.com/platform/detail.html?id=86859", "Cover": "//i1.hdslb.com/bfs/openplatform/202406/LQOrzPac1717473481789.png"}, {"开始时间": "2024-07-27", "名称": "杭州·第五人格only", "地点": "望江东路333号 杭州瑞莱克斯大酒店", "具体时间范围": "2024.07.27 10:00-07.27 17:00", "想去人数": 1231, "最低票价": 60.0, "Link": "https://show.bilibili.com/platform/detail.html?id=86861", "Cover": "//i1.hdslb.com/bfs/openplatform/202406/ZiqYUjIt1717471158198.jpeg"}, {"开始时间": "2024-07-27", "名称": "杭州·萌忧 原崩铁only", "地点": "康候圣街99号 顺丰创新中心", "具体时间范围": "2024.07.27 10:30-07.27 17:00", "想去人数": 853, "最低票价": 50.0, "Link": "https://show.bilibili.com/platform/detail.html?id=87913", "Cover": "//i2.hdslb.com/bfs/openplatform/202406/21TFRkof1717573235775.jpeg"}, {"开始时间": "2024-07-27", "名称": "杭州·黄西全新脱口秀专场《水土不服》", "地点": "延安路279号 浙江胜利剧院", "具体时间范围": "2024.07.27 14:30-07.27 21:30", "想去人数": 5, "最低票价": 180.0, "Link": "https://show.bilibili.com/platform/detail.html?id=85935", "Cover": "//i2.hdslb.com/bfs/openplatform/202405/9YqhR4Ke1716191781870.jpeg"}, {"开始时间": "2024-07-28", "名称": "杭州·火影忍者only", "地点": "康候圣街99号 顺丰创新中心", "具体时间范围": "2024.07.28 09:00-07.28 18:00", "想去人数": 2019, "最低票价": 75.0, "Link": "https://show.bilibili.com/platform/detail.html?id=84243", "Cover": "//i1.hdslb.com/bfs/openplatform/202405/isG309e51715657222196.jpeg"}, {"开始时间": "2024-07-28", "名称": "杭州·第三届百合Only·同好交流", "地点": "望江东路333号 杭州瑞莱克斯大酒店", "具体时间范围": "2024.07.28 10:00-07.28 16:00", "想去人数": 422, "最低票价": 46.0, "Link": "https://show.bilibili.com/platform/detail.html?id=85895", "Cover": "//i2.hdslb.com/bfs/openplatform/202405/fP3O6LYz1715844791584.jpeg"}, {"开始时间": "2024-07-31", "名称": "杭州·乙游Camerata杭州2.0", "地点": "杭海路601号江和美海洋广场1层 嘉宝丽酒店", "具体时间范围": "2024.07.31 10:00-07.31 17:00", "想去人数": 614, "最低票价": 68.0, "Link": "https://show.bilibili.com/platform/detail.html?id=86777", "Cover": "//i1.hdslb.com/bfs/openplatform/202406/AparhR671719474456997.jpeg"}, {"开始时间": "2024-08-03", "名称": "杭州·AP动漫游戏嘉年华", "地点": "沈半路171号 Tcar汽车文化主题公园", "具体时间范围": "2024.08.03 09:00-08.04 17:00", "想去人数": 2649, "最低票价": 70.0, "Link": "https://show.bilibili.com/platform/detail.html?id=85527", "Cover": "//i2.hdslb.com/bfs/openplatform/202405/JbVl16OE1715676665714.jpeg"}, {"开始时间": "2024-08-03", "名称": "杭州·文豪野犬ONLY", "地点": "康候圣街99号 顺丰创新中心", "具体时间范围": "2024.08.03 10:00-08.03 17:00", "想去人数": 183, "最低票价": 79.0, "Link": "https://show.bilibili.com/platform/detail.html?id=87115", "Cover": "//i2.hdslb.com/bfs/openplatform/202406/MK5CNQJ61717579320994.jpeg"}, {"开始时间": "2024-08-03", "名称": "杭州·梦漫星河动漫展", "地点": "阳城路雅澳杭州电商产业园西侧约200米 杭州大会展中心", "具体时间范围": "2024.08.03 10:00-08.04 17:00", "想去人数": 1735, "最低票价": 68.0, "Link": "https://show.bilibili.com/platform/detail.html?id=82836", "Cover": "//i0.hdslb.com/bfs/openplatform/202403/VFfQUJdD1711700169290.jpeg"}, {"开始时间": "2024-08-04", "名称": "杭州·井草圣二 2024《夏日独白》指弹吉他音乐会", "地点": "中山南路77号尚城1157利星3楼 MAO Livehouse（杭州）", "具体时间范围": "2024.08.04 19:30-08.04 21:00", "想去人数": 5, "最低票价": 260.0, "Link": "https://show.bilibili.com/platform/detail.html?id=86939", "Cover": "//i2.hdslb.com/bfs/openplatform/202406/12K7MVMZ1717643805476.jpeg"}, {"开始时间": "2024-08-10", "名称": "杭州·SK-LiLi综合同人展 × KK WORLD MINI快看漫画乐园", "地点": "鸿泰路与明月桥路交汇处东南角方位(杭港地铁1号线/杭州地铁4号线彭埠站D口20米) 港龙悠乐城", "具体时间范围": "2024.08.10 10:00-08.11 17:00", "想去人数": 793, "最低票价": 68.0, "Link": "https://show.bilibili.com/platform/detail.html?id=88062", "Cover": "//i2.hdslb.com/bfs/openplatform/202406/xlLi5AXx1719324778808.jpeg"}, {"开始时间": "2024-08-10", "名称": "杭州·《LALALAND爱乐之城》浪漫主题音乐会", "地点": "武林路77号 浙江省文化馆小剧场（原群艺馆小剧场）", "具体时间范围": "2024.08.10 14:30-08.10 16:00", "想去人数": 10, "最低票价": 100.0, "Link": "https://show.bilibili.com/platform/detail.html?id=86928", "Cover": "//i2.hdslb.com/bfs/openplatform/202406/WRJvvYJV1717575030302.jpeg"}, {"开始时间": "2024-08-10", "名称": "杭州·【七夕巨献·早鸟6折】真的爱你”致敬Beyond·黄家驹31周年演唱会·630乐团再现91殿堂级演出", "地点": "湖墅南路136-138号 浙话艺术剧院", "具体时间范围": "2024.08.10 19:30-08.10 21:30", "想去人数": 5, "最低票价": 60.0, "Link": "https://show.bilibili.com/platform/detail.html?id=85333", "Cover": "//i1.hdslb.com/bfs/openplatform/202405/uYt32zt21715221330023.jpeg"}, {"开始时间": "2024-08-10", "名称": "杭州·原神X崩坏X星铁旅行盛宴·首展", "地点": "德胜东路2539号 梦马汽车小镇", "具体时间范围": "2024.08.10 10:00-08.11 17:00", "想去人数": 45, "最低票价": 65.0, "Link": "https://show.bilibili.com/platform/detail.html?id=88429", "Cover": "//i1.hdslb.com/bfs/openplatform/202407/1oKYAwlD1719816495200.png"}, {"开始时间": "2024-08-10", "名称": "杭州·原神X星铁X绝区零only", "地点": "望江东路333号 杭州瑞莱克斯大酒店", "具体时间范围": "2024.08.10 10:00-08.10 17:00", "想去人数": 912, "最低票价": 60.0, "Link": "https://show.bilibili.com/platform/detail.html?id=82754", "Cover": "//i1.hdslb.com/bfs/openplatform/202403/qA0LNJuF1710234461030.jpeg"}, {"开始时间": "2024-08-10", "名称": "杭州·吹响号角狩猎吧—怪物猎人&最终幻想&塞尔达 热血游戏视听音乐会", "地点": "杭州市江干区新业路39号 杭州大剧院(音乐厅)", "具体时间范围": "2024.08.10 19:30-08.10 21:00", "想去人数": 67, "最低票价": 180.0, "Link": "https://show.bilibili.com/platform/detail.html?id=84879", "Cover": "//i0.hdslb.com/bfs/openplatform/202404/jJcWHuGa1714010818763.jpeg"}, {"开始时间": "2024-08-10", "名称": "杭州·追逐动漫的旋律—二次元音符的魔法 经典动漫ACG视听音乐会", "地点": "杭州市江干区新业路39号 杭州大剧院(音乐厅)", "具体时间范围": "2024.08.10 14:30-08.10 16:00", "想去人数": 67, "最低票价": 180.0, "Link": "https://show.bilibili.com/platform/detail.html?id=84898", "Cover": "//i2.hdslb.com/bfs/openplatform/202404/75j1xIzA1714102078044.jpeg"}, {"开始时间": "2024-08-10", "名称": "杭州·造梦探险家城堡二次元同好会", "地点": "大岭山路156号 爱丽芬城堡", "具体时间范围": "2024.08.10 10:00-08.10 22:00", "想去人数": 589, "最低票价": 38.0, "Link": "https://show.bilibili.com/platform/detail.html?id=86432", "Cover": "//i2.hdslb.com/bfs/openplatform/202405/xWUy30Ns1716783723057.jpeg"}, {"开始时间": "2024-08-17", "名称": "杭州·动漫作品主题音乐会-《火影忍者》《海贼王》《灌篮高手》", "地点": "曙光路31号 浙江音乐厅", "具体时间范围": "2024.08.17 19:30-08.17 21:00", "想去人数": 42, "最低票价": 100.0, "Link": "https://show.bilibili.com/platform/detail.html?id=85891", "Cover": "//i1.hdslb.com/bfs/openplatform/202405/ei0H7pZr1716099647338.jpeg"}, {"开始时间": "2024-08-17", "名称": "浙江·马娘ONLY03-晴风游憩", "地点": "康候圣街99号 顺丰创新中心", "具体时间范围": "2024.08.17 10:00-08.17 17:00", "想去人数": 234, "最低票价": 68.0, "Link": "https://show.bilibili.com/platform/detail.html?id=86529", "Cover": "//i1.hdslb.com/bfs/openplatform/202405/21d6moub1716799089058.jpeg"}, {"开始时间": "2024-08-18", "名称": "杭州·少女番only3.0", "地点": "凤起东路211号 名人名家宴会艺术中心(顺福店)", "具体时间范围": "2024.08.18 10:00-08.18 17:00", "想去人数": 81, "最低票价": 89.0, "Link": "https://show.bilibili.com/platform/detail.html?id=87676", "Cover": "//i1.hdslb.com/bfs/openplatform/202406/VHJXciCn1718433428129.jpeg"}, {"开始时间": "2024-08-18", "名称": "浙江·蔚蓝档案ONLY02-夏末狂欢！", "地点": "康候圣街99号 顺丰创新中心", "具体时间范围": "2024.08.18 10:00-08.18 17:00", "想去人数": 505, "最低票价": 68.0, "Link": "https://show.bilibili.com/platform/detail.html?id=86594", "Cover": "//i1.hdslb.com/bfs/openplatform/202405/TVvJFURG1716799911888.jpeg"}, {"开始时间": "2024-08-24", "名称": "杭州·D3动漫游戏嘉年华", "地点": "德胜东路2539号 梦马汽车小镇", "具体时间范围": "2024.08.24 10:00-08.24 17:00", "想去人数": 575, "最低票价": 50.0, "Link": "https://show.bilibili.com/platform/detail.html?id=84912", "Cover": "//i0.hdslb.com/bfs/openplatform/202406/LC5aplda1718697399055.jpeg"}, {"开始时间": "2024-08-24", "名称": "杭州·奶司的小人国娃展Nice Mini World", "地点": "凤起东路211号 名人名家宴会艺术中心(顺福店)", "具体时间范围": "2024.08.24 10:30-08.24 17:00", "想去人数": 27, "最低票价": 60.0, "Link": "https://show.bilibili.com/platform/detail.html?id=86954", "Cover": "//i0.hdslb.com/bfs/openplatform/202406/aeSvo0X71717659096631.png"}, {"开始时间": "2024-08-24", "名称": "杭州·萌忧·原崩铁only", "地点": "康候圣街99号 顺丰创新中心", "具体时间范围": "2024.08.24 10:30-08.24 17:00", "想去人数": 894, "最低票价": 50.0, "Link": "https://show.bilibili.com/platform/detail.html?id=87293", "Cover": "//i2.hdslb.com/bfs/openplatform/202406/rQFz5smR1717475284585.jpeg"}, {"开始时间": "2024-08-24", "名称": "杭州·金魂ONLY", "地点": "金一路79号 XPACE湾区数字公园", "具体时间范围": "2024.08.24 10:00-08.24 18:00", "想去人数": 235, "最低票价": 78.0, "Link": "https://show.bilibili.com/platform/detail.html?id=87230", "Cover": "//i2.hdslb.com/bfs/openplatform/202406/SfNdoHfv1718176444920.png"}, {"开始时间": "2024-11-01", "名称": "杭州·阿加莎•克里斯蒂经典悬疑剧《无人生还》", "地点": "武林广场29号 杭州剧院", "具体时间范围": "2024.11.01 19:30-11.03 17:00", "想去人数": 59, "最低票价": 380.0, "Link": "https://show.bilibili.com/platform/detail.html?id=82776", "Cover": "//i0.hdslb.com/bfs/openplatform/202403/K55FY9vh1710298068131.jpeg"}]}